{
  "app": {
    "[project]/src/app/(shell)/analytics/page": [
      "static/media/8a480f0b521d4e75-s.p.1qq4vpdcun5oj.woff2",
      "static/media/caa3a2e1cccd8315-s.p.0wgildi0cnwt9.woff2",
      "static/media/797e433ab948586e-s.p.0r6juujl39pe6.woff2"
    ],
    "[project]/src/app/(shell)/chats/page": [
      "static/media/8a480f0b521d4e75-s.p.1qq4vpdcun5oj.woff2",
      "static/media/caa3a2e1cccd8315-s.p.0wgildi0cnwt9.woff2",
      "static/media/797e433ab948586e-s.p.0r6juujl39pe6.woff2"
    ],
    "[project]/src/app/(shell)/feed/page": [
      "static/media/8a480f0b521d4e75-s.p.1qq4vpdcun5oj.woff2",
      "static/media/caa3a2e1cccd8315-s.p.0wgildi0cnwt9.woff2",
      "static/media/797e433ab948586e-s.p.0r6juujl39pe6.woff2"
    ],
    "[project]/src/app/(shell)/gchat/page": [
      "static/media/8a480f0b521d4e75-s.p.1qq4vpdcun5oj.woff2",
      "static/media/caa3a2e1cccd8315-s.p.0wgildi0cnwt9.woff2",
      "static/media/797e433ab948586e-s.p.0r6juujl39pe6.woff2"
    ],
    "[project]/src/app/(shell)/note/global/[id]/page": [
      "static/media/8a480f0b521d4e75-s.p.1qq4vpdcun5oj.woff2",
      "static/media/caa3a2e1cccd8315-s.p.0wgildi0cnwt9.woff2",
      "static/media/797e433ab948586e-s.p.0r6juujl39pe6.woff2"
    ],
    "[project]/src/app/(shell)/note/new/page": [
      "static/media/8a480f0b521d4e75-s.p.1qq4vpdcun5oj.woff2",
      "static/media/caa3a2e1cccd8315-s.p.0wgildi0cnwt9.woff2",
      "static/media/797e433ab948586e-s.p.0r6juujl39pe6.woff2"
    ],
    "[project]/src/app/(shell)/note/post/[postId]/[noteId]/page": [
      "static/media/8a480f0b521d4e75-s.p.1qq4vpdcun5oj.woff2",
      "static/media/caa3a2e1cccd8315-s.p.0wgildi0cnwt9.woff2",
      "static/media/797e433ab948586e-s.p.0r6juujl39pe6.woff2"
    ],
    "[project]/src/app/(shell)/notes/page": [
      "static/media/8a480f0b521d4e75-s.p.1qq4vpdcun5oj.woff2",
      "static/media/caa3a2e1cccd8315-s.p.0wgildi0cnwt9.woff2",
      "static/media/797e433ab948586e-s.p.0r6juujl39pe6.woff2"
    ],
    "[project]/src/app/(shell)/page": [
      "static/media/8a480f0b521d4e75-s.p.1qq4vpdcun5oj.woff2",
      "static/media/caa3a2e1cccd8315-s.p.0wgildi0cnwt9.woff2",
      "static/media/797e433ab948586e-s.p.0r6juujl39pe6.woff2"
    ],
    "[project]/src/app/(shell)/post/[id]/page": [
      "static/media/8a480f0b521d4e75-s.p.1qq4vpdcun5oj.woff2",
      "static/media/caa3a2e1cccd8315-s.p.0wgildi0cnwt9.woff2",
      "static/media/797e433ab948586e-s.p.0r6juujl39pe6.woff2"
    ],
    "[project]/src/app/(shell)/profile/page": [
      "static/media/8a480f0b521d4e75-s.p.1qq4vpdcun5oj.woff2",
      "static/media/caa3a2e1cccd8315-s.p.0wgildi0cnwt9.woff2",
      "static/media/797e433ab948586e-s.p.0r6juujl39pe6.woff2"
    ],
    "[project]/src/app/_not-found/page": [
      "static/media/8a480f0b521d4e75-s.p.1qq4vpdcun5oj.woff2",
      "static/media/caa3a2e1cccd8315-s.p.0wgildi0cnwt9.woff2",
      "static/media/797e433ab948586e-s.p.0r6juujl39pe6.woff2"
    ]
  },
  "appUsingSizeAdjust": true,
  "pages": {},
  "pagesUsingSizeAdjust": false
}